{
    "activeSetID": "etti",
    "activeSetName": "Missing Person: Etti Morales",
    "sets": [
        {
            "id": "template",
            "name": "Template Challenge Set",
            "description": "An empty template challenge set for author reference",
            "path": "./config/template.json"
        },
        {
            "id": "etti",
            "name": "Missing Person: Etti Morales",
            "description": "My first CTF revolving around a missing person's case of a college student, contains two seperate endings",
            "path": "./challenge_sets/etti.json"
        }
    ]
}